dockie/__init__.py
tq_dockie_db-1.0.dist-info/LICENSE
tq_dockie_db-1.0.dist-info/METADATA
tq_dockie_db-1.0.dist-info/WHEEL
tq_dockie_db-1.0.dist-info/top_level.txt
tq_dockie_db-1.0.dist-info/RECORD
