Metadata-Version: 2.1
Name: tq-dockie-db
Version: 1.0
Summary: DockieDb is a simple in-memory document database.
Home-page: https://github.com/farooq-teqniqly/tq-dockie-db
Author: Teqniqly
Author-email: farooq@teqniqly.com
License: MIT
Project-URL: GitHub, https://github.com/farooq-teqniqly/tq-dockie-db
Platform: UNKNOWN
Classifier: Development Status :: 5 - Production/Stable
Classifier: Programming Language :: Python
Classifier: Programming Language :: Python :: 3 :: Only
Classifier: Intended Audience :: Developers
Classifier: License :: OSI Approved :: MIT License
Classifier: Topic :: Software Development :: Libraries :: Python Modules
Classifier: Topic :: Database :: Database Engines/Servers
Requires-Python: >=3.9
License-File: LICENSE
Requires-Dist: dictquery
